README.md
setup.py
datahub_extras/__init__.py
datahub_extras/datahub_extras.py
datahub_extras.egg-info/PKG-INFO
datahub_extras.egg-info/SOURCES.txt
datahub_extras.egg-info/dependency_links.txt
datahub_extras.egg-info/requires.txt
datahub_extras.egg-info/top_level.txt