Metadata-Version: 1.0
Name: datahub-extras
Version: 0.0.2
Summary: This package extends datahub and makes it easier to interact with datahub APIs
Home-page: UNKNOWN
Author: Hugh Nguyen
Author-email: UNKNOWN
License: UNKNOWN
Platform: UNKNOWN
